Metadata-Version: 1.0
Name: ftdpack
Version: 1.0
Summary: package to access failure to deliver data
Home-page: https://github.com/jc22dora/ftdpack
Author: John Doran
Author-email: jdorrkng@jdoran.dev
License: MIT
Platform: UNKNOWN
